{
    "id": "1140",
    "palavra": "CAPITÃO",
    "acepcao": "Jogador que representa a equipe durante a competição, e, entre outras funções, é encarregado de manter os contato necessários com o juiz.",
    "exemplo": "O capitão do grupo de futebol dele é legal.",
    "video": "capitao2Sm_Prog001.mp4",
    "libras": "FUTEBOL GRUPO DEL@ CAPITÃO LEGAL.",
    "img": "capitao2Sm_Prog001.jpg",
    "assunto": "8",
    "assunto_title": "ESPORTE/DIVERSÃO",
    "classe": "SUBSTANTIVO",
    "url": "cg32.jpg",
    "origem": "nacional",
    "mao": "cg32.jpg"
}