{
    "id": "1151",
    "palavra": "CARBURADOR",
    "acepcao": "Aparelho onde o combustível se mistura com o ar, para garantir o bom funcionamento de um motor de explosão.",
    "exemplo": "O carburador do meu carro pifou.",
    "video": "carburadorSm_Prog001.mp4",
    "libras": "CARRO ME@ CARBURADOR PIFAR.",
    "img": "carburadorSm_Prog001.jpg",
    "assunto": "21",
    "assunto_title": "APARELHO/MÁQUINA",
    "classe": "SUBSTANTIVO",
    "url": "cg64.jpg",
    "origem": "nacional",
    "mao": "cg64.jpg"
}