{
    "id": "1302",
    "palavra": "CHOCALHO",
    "acepcao": "Instrumento musical de percussão, que costuma ser copiado e adaptado como um brinquedo para o bebê.",
    "exemplo": "Eu comprei um chocalho e presenteei o meu sobrinho bebê.",
    "video": "chocalhoSm_Prog001.mp4",
    "libras": "EU COMPRAR CHOCALHO 1sPRESENTEAR3s SOBRINH@ BEBÊ.",
    "img": "chocalhoSm_Prog001.jpg",
    "assunto": "8",
    "assunto_title": "ESPORTE/DIVERSÃO",
    "classe": "SUBSTANTIVO",
    "url": "cg05.jpg",
    "origem": "nacional",
    "mao": "cg05.jpg"
}