{
    "id": "1802",
    "palavra": "DEPENDENTE",
    "acepcao": "Aquele que precisa de outro para custear sua sobrevivência; filhos menores, doentes, adultos inativos, idosos, que dependem de algum tipo de auxílio.",
    "exemplo": "Aquele homem é dependente da mãe dele.",
    "video": "dependenteSm_Prog001.mp4",
    "libras": "HOMEM AQUEL@ M-Ã-E DEPENDENTE.",
    "img": "dependenteSm_Prog001.jpg",
    "assunto": "23",
    "assunto_title": "FAMÍLIA",
    "classe": "ADJETIVO",
    "url": "cg34.jpg",
    "origem": "nacional",
    "mao": "cg34.jpg"
}