{
    "id": "223",
    "palavra": "AGULHA2",
    "acepcao": "Peça fina e pontiaguda, que é acoplada a uma seringa, para injetar líquidos em determinadas regiões do corpo.",
    "exemplo": "Eu tenho medo de tomar injeção com agulha grande.",
    "video": "agulhar2Sm_Prog001.mp4",
    "libras": "EU MEDO objeto-fino-pequeno^INJEÇÃO GRANDE.",
    "img": "agulha2Sm_Prog001.jpg",
    "assunto": "28",
    "assunto_title": "HIGIENE/SAÚDE",
    "classe": "SUBSTANTIVO",
    "url": "cg17.jpg",
    "origem": "nacional",
    "mao": "cg17.jpg"
}