{
    "id": "2702",
    "palavra": "GASOSO",
    "acepcao": "Estado da água que decorre da ebulição, quando a pressão de vapor do líquido iguala a pressão atmosférica.",
    "exemplo": "Na aula de ciências foi explicado como a água que ferve se transforma em gasoso.",
    "video": "gasosoSm_Prog001.mp4",
    "libras": "AULA CIÊNCIAS PROFESSOR@ EXPLICAR ÁGUA FERVER TRANSFORMAR GASOSO.",
    "img": "gasosoSm_Prog001.jpg",
    "assunto": "29",
    "assunto_title": "MATÉRIA/SUBSTÂNCIA",
    "classe": "ADJETIVO",
    "url": "cg57.jpg",
    "origem": "nacional",
    "mao": "cg57.jpg"
}