{
    "id": "2713",
    "palavra": "GELATINA",
    "acepcao": "Substância que forma uma geléia mais ou menos consistente, quando dissolvida em água quente. É preparada com a proteína viscosa existente em tecidos fibrosos e ossos de animais.",
    "exemplo": "Gelatina é muito gostosa.",
    "video": "gelatinaSm_Prog001.mp4",
    "libras": "GELATINA GOSTOS@muito.",
    "img": "gelatinaSm_Prog001.jpg",
    "assunto": "29",
    "assunto_title": "MATÉRIA/SUBSTÂNCIA",
    "classe": "SUBSTANTIVO",
    "url": "cg46a.jpg",
    "origem": "nacional",
    "mao": "cg46a.jpg"
}