{
    "id": "2777",
    "palavra": "GRADE2",
    "acepcao": "Armação de tiras de ferro, madeira ou outro material, dispostas lado a lado ou cruzadas, usada para proteger ou isolar uma área.",
    "exemplo": "Preciso pintar a grade da janela da minha casa.",
    "video": "grade2Sm_Prog001.mp4",
    "libras": "GRADE JANELA CASA ME@ PRECISAR PINTAR.",
    "img": "grade2Sm_Prog001.jpg",
    "assunto": "22",
    "assunto_title": "CASA",
    "classe": "SUBSTANTIVO",
    "url": "cg46a.jpg",
    "origem": "nacional",
    "mao": "cg46a.jpg"
}