{
    "id": "2854",
    "palavra": "HERPES",
    "acepcao": "Afecção da pele e das mucosas, caracterizada por grupos de vesículas sobre uma base inflamada, alternando com intervalos de pele completamente sã.",
    "exemplo": "Meu marido sempre aparece com herpes na boca.",
    "video": "herpesSm_Prog001.mp4",
    "libras": "ME@ ESPOS@ APARECER coisa-volumosaBOCA SEMPRE.",
    "img": "herpesSm_Prog001.jpg",
    "assunto": "28",
    "assunto_title": "HIGIENE/SAÚDE",
    "classe": "SUBSTANTIVO",
    "url": "cg45.jpg",
    "origem": "nacional",
    "mao": "cg45.jpg"
}