{
    "id": "3040",
    "palavra": "INTERPRETAÇÃO",
    "acepcao": "Tradução, versão ou explicação de textos em língua estrangeira ou de sinais.",
    "exemplo": "Aquele homem fez uma perfeita interpretação de inglês para português.",
    "video": "interpretacaoSm_Prog001.mp4",
    "libras": "AQUEL@ HOMEM INTERPRETAÇÃO INGLÊS PORTUGUÊS PERFEIT@.",
    "img": "interpretacaoSm_Prog001.jpg",
    "assunto": "1",
    "assunto_title": "NENHUM",
    "classe": "SUBSTANTIVO",
    "url": "cg63.jpg",
    "origem": "nacional",
    "mao": "cg63.jpg"
}