{
    "id": "3153",
    "palavra": "JÚRI",
    "acepcao": "Tribunal judiciário presidido por um juiz de direito. É composto por sete cidadãos, sorteados entre 21 de notória idoneidade.",
    "exemplo": "O Júri sentenciou que ele era culpado.",
    "video": "juriSm_Prog001.mp4",
    "libras": "JÚRI DECIDIR ELE CULPAD@.",
    "img": "juriSm_Prog001.jpg",
    "assunto": "1",
    "assunto_title": "NENHUM",
    "classe": "SUBSTANTIVO",
    "url": "cg53a.jpg",
    "origem": "nacional",
    "mao": "cg53a.jpg"
}