{
    "id": "3258",
    "palavra": "LEITO",
    "acepcao": "Modo como é chamada a peça do mobiliário em que o paciente é acomodado durante sua permanência em um hospital.",
    "exemplo": "No hospital municipal faltam leitos e outras coisas.",
    "video": "leitoSm_Prog001.mp4",
    "libras": "HOSPITAL MUNICIPAL TER-NÃO LEITO FALTA COISA.",
    "img": "leitoSm_Prog001.jpg",
    "assunto": "1",
    "assunto_title": "NENHUM",
    "classe": "SUBSTANTIVO",
    "url": "cg37a.jpg",
    "origem": "nacional",
    "mao": "cg37a.jpg"
}