{
    "id": "3273",
    "palavra": "LEPRA",
    "acepcao": "Doença infecciosa e transmissível, caracterizada por lesões no sistema nervoso periférico, nas membranas mucosas e na pele.",
    "exemplo": "Há muitos anos, as pessoas morriam com lepra, pois não havia remédio para curá-las.",
    "video": "lepraSm_Prog001.mp4",
    "libras": "ANTIGAMENTE PESSOA MORRERcontinuativo LEPRA PORQUE TER-NÃO REMÉDIO CURAR.",
    "img": "lepraSm_Prog001.jpg",
    "assunto": "28",
    "assunto_title": "HIGIENE/SAÚDE",
    "classe": "SUBSTANTIVO",
    "url": "cg44.jpg",
    "origem": "nacional",
    "mao": "cg44.jpg"
}