{
    "id": "3351",
    "palavra": "LIXO",
    "acepcao": "Entulho; depósito para colocar tudo que é imprestável.",
    "exemplo": "Eu sempre vejo as pessoas jogando papel na rua com preguiça de jogar no lixo.",
    "video": "lixo2Sm_Prog001.mp4",
    "libras": "EU VER PESSOA SEMPRE PAPEL R-U-A JOGAR PREGUIÇA LIXO JOGAR.",
    "img": "lixo2Sm_Prog001.jpg",
    "assunto": "28",
    "assunto_title": "HIGIENE/SAÚDE",
    "classe": "SUBSTANTIVO",
    "url": "cg36.jpg",
    "origem": "nacional",
    "mao": "cg36.jpg"
}