{
    "id": "337",
    "palavra": "AMÉRICA",
    "acepcao": "Continente formado pela América do Norte, a América Central e a América do Sul.",
    "exemplo": "Eu já viajei por todo o continente americano.",
    "video": "americaSm_Prog001.mp4",
    "libras": "EU JÁ VIAJARcontinuativo AMÉRICA TOD@.",
    "img": "americaSm_Prog001.jpg",
    "assunto": "4",
    "assunto_title": "PAÍS/ESTADO/CIDADE",
    "classe": "SUBSTANTIVO",
    "url": "cg64.jpg",
    "origem": "nacional",
    "mao": "cg64.jpg"
}