{
    "id": "3472",
    "palavra": "MANIFESTAR1",
    "acepcao": "Expressar um sentimento, idéia ou opinião.",
    "exemplo": "Muitas pessoas se manifestam contra o governo por causa dos baixos salários.",
    "video": "manifestar1Sm_Prog001.mp4",
    "libras": "PESSOA MUIT@ MANIFESTAR CONTRA GOVERNO SALÁRIO POUC@.",
    "img": "manifestar1Sm_Prog001.jpg",
    "assunto": "1",
    "assunto_title": "NENHUM",
    "classe": "VERBO",
    "url": "cg05.jpg",
    "origem": "nacional",
    "mao": "cg05.jpg"
}