{
    "id": "3529",
    "palavra": "MATERIAL2",
    "acepcao": "Equipamentos, utensílios, etc necessários para um determinado fim (material escolar, de construção, de escritório, de casa, etc)",
    "exemplo": "Papai já comprou os materiais, ele vai construir uma casa nova.",
    "video": "materialSm_Prog001.mp4",
    "libras": "P-A-I JÁ COMPRAR MATERIAL VÁRI@S V-A-I CONSTRUIR CASA NOV@.",
    "img": "materialSm_Prog001.jpg",
    "assunto": "1",
    "assunto_title": "NENHUM",
    "classe": "SUBSTANTIVO",
    "url": "cg14.jpg",
    "origem": "nacional",
    "mao": "cg14.jpg"
}