{
    "id": "3720",
    "palavra": "MUNDO",
    "acepcao": "A Terra e o astros considerados como um todo organizado; o Universo; globo terrestre.",
    "exemplo": "O futebol da seleção brasileira é cinco vezes campeão do mundo.",
    "video": "mundoSm_Prog001.mp4",
    "libras": "FUTEBOL BRASIL MUNDO PENTACAMPEÃO.",
    "img": "mundoSm_Prog001.jpg",
    "assunto": "20",
    "assunto_title": "PLANTA/FLOR/NATUREZA",
    "classe": "SUBSTANTIVO",
    "url": "cg01.jpg",
    "origem": "nacional",
    "mao": "cg01.jpg"
}