{
    "id": "4033",
    "palavra": "PAPELÃO",
    "acepcao": "Papel duro e encorpado, próprio para a fabricação de embalagens.",
    "exemplo": "Vou procurar uma caixa de papelão e colocarei livros para mudar.",
    "video": "papelaoSm_Prog001.mp4",
    "libras": "EU PROCURAR CAIXA PAPEL^GROSSO LIVRO coisa-planaCOLOCAR.",
    "img": "papelaoSm_Prog001.jpg",
    "assunto": "1",
    "assunto_title": "NENHUM",
    "classe": "SUBSTANTIVO",
    "url": "cg08a.jpg",
    "origem": "nacional",
    "mao": "cg08a.jpg"
}