{
    "id": "4128",
    "palavra": "PAZ",
    "acepcao": "Bom entendimento; harmonia; tranqüilidade; ausência de luta; inexistência de guerra, violência ou perturbação social; cessação de hostilidades.",
    "exemplo": "Eu quero que o mundo tenha paz.",
    "video": "pazSm_Prog001.mp4",
    "libras": "EU QUERER MUNDO P-A-Z.",
    "img": "pazSm_Prog001.jpg",
    "assunto": "1",
    "assunto_title": "NENHUM",
    "classe": "SUBSTANTIVO",
    "url": "cg01.jpg",
    "origem": "nacional",
    "mao": "cg01.jpg"
}