{
    "id": "4437",
    "palavra": "PRATELEIRA",
    "acepcao": "Móvel apropriado para a exposição de livros, discos, CDs e outros objetos.",
    "exemplo": "Chamei o meu filho para me ajudar a colocar coisas na prateleira do quarto dele.",
    "video": "prateleiraSm_Prog001.mp4",
    "libras": "EU CHAMAR ME@ FILH@ 2sAJUDAR1s PRATELEIRA COISA COLOCAR QUARTO DEL@.",
    "img": "prateleiraSm_Prog001.jpg",
    "assunto": "22",
    "assunto_title": "CASA",
    "classe": "SUBSTANTIVO",
    "url": "cg61.jpg",
    "origem": "nacional",
    "mao": "cg61.jpg"
}