{
    "id": "4596",
    "palavra": "QUADRA",
    "acepcao": "Espaço, geralmente com dimensões oficiais, usado para a prática de esportes individuais ou coletivos.",
    "exemplo": "Sábado que vem terá voleibol na quadra da Associação.",
    "video": "quadraSm_Prog001.mp4",
    "libras": "SÁBADO PRÓXIMO TER VOLEIBOL LÁ QUADRA ASSOCIAÇÃO.",
    "img": "quadraSm_Prog001.jpg",
    "assunto": "8",
    "assunto_title": "ESPORTE/DIVERSÃO",
    "classe": "SUBSTANTIVO",
    "url": "cg14.jpg",
    "origem": "nacional",
    "mao": "cg14.jpg"
}