{
    "id": "5149",
    "palavra": "SOBREMESA",
    "acepcao": "Iguaria delicada e leve (doce ou fruta) com que se termina uma refeição.",
    "exemplo": "Meu filho sempre come sobremesa de chocolate.",
    "video": "sobremesaSm_Prog001.mp4",
    "libras": "FILH@ ME@ SEMPRE COMER SOBREMESA CHOCOLATE.",
    "img": "sobremesaSm_Prog001.jpg",
    "assunto": "31",
    "assunto_title": "ALIMENTO/BEBIDA",
    "classe": "SUBSTANTIVO",
    "url": "cg62.jpg",
    "origem": "nacional",
    "mao": "cg62.jpg"
}