{
    "id": "5345",
    "palavra": "TÍQUETE",
    "acepcao": "Pequeno bilhete impresso, que dá ao portador gratuidade em determinadas situações, como nos transportes coletivos ou restaurantes.",
    "exemplo": "No meu trabalho, eu recebo tíquete para o restaurante.",
    "video": "tiqueteSm_Prog001.mp4",
    "libras": "ME@ TRABALHO EU RECEBER RESTAURANTE TÍQUETE.",
    "img": "tiqueteSm_Prog001.jpg",
    "assunto": "6",
    "assunto_title": "NUMERAL/DINHEIRO",
    "classe": "SUBSTANTIVO",
    "url": "cg18a.jpg",
    "origem": "nacional",
    "mao": "cg18a.jpg"
}