{
    "id": "5491",
    "palavra": "TUBERCULOSE",
    "acepcao": "Doença infecto-contagiosa e endêmica, provocada pelo bacilo de Koch, capaz de atingir quase todos os tecidos do corpo, especialmente os pulmões.",
    "exemplo": "Meu primo está com tuberculose.",
    "video": "tuberculoseSm_Prog001.mp4",
    "libras": "ME@ PRIM@ DOENTE TUBERCULOSE.",
    "img": "tuberculoseSm_Prog001.jpg",
    "assunto": "28",
    "assunto_title": "HIGIENE/SAÚDE",
    "classe": "SUBSTANTIVO",
    "url": "cg02.jpg",
    "origem": "nacional",
    "mao": "cg02.jpg"
}