{
    "id": "5561",
    "palavra": "VAGÃO",
    "acepcao": "Compartimento do trem das estradas de ferro, para o transporte de passageiros, mercadorias ou gado.",
    "exemplo": "aquele trem tem vagão-dormitório e restaurante de luxo.",
    "video": "vagaoSm_Prog001.mp4",
    "libras": "TREM AQUELE veículo-enfileiradoTREM DORMIR RESTAURANTE LUX@ TER.",
    "img": "vagaoSm_Prog001.jpg",
    "assunto": "24",
    "assunto_title": "TRANPORTE/VEÍCULO",
    "classe": "SUBSTANTIVO",
    "url": "cg31.jpg",
    "origem": "nacional",
    "mao": "cg31.jpg"
}