{
    "id": "558",
    "palavra": "ARTICULAR",
    "acepcao": "Tomar todas as providências; organizar; manter contato com pessoas envolvidas em determinado assunto.",
    "exemplo": "Quem está articulando a sua candidatura para a presidência do clube?",
    "video": "articularSm_Prog001.mp4",
    "libras": "CLUBE CANDIDATURA PRESIDÊNCIA RESPONSÁVEL ARTICULAR Q-U-M?",
    "img": "articularSm_Prog001.jpg",
    "assunto": "1",
    "assunto_title": "NENHUM",
    "classe": "VERBO",
    "url": "cg49.jpg",
    "origem": "nacional",
    "mao": "cg49.jpg"
}