{
    "id": "573",
    "palavra": "ASPIRADOR DE PÓ",
    "acepcao": "Aparelho eletrodoméstico que retira o pó de móveis, tapetes, sofás e outros espaços, depositando-o em uma bolsa portátil, por meio de sucção.",
    "exemplo": "No Natal, meu marido me deu um aspirador de pó de presente.",
    "video": "aspirador-de-poSm_Prog001.mp4",
    "libras": "MARID@ ME@ NATAL 3SPRESENTEAR1s ASPIRADOR-DE-PÓ.",
    "img": "aspirador-de-poSm_Prog001.jpg",
    "assunto": "21",
    "assunto_title": "APARELHO/MÁQUINA",
    "classe": "SUBSTANTIVO",
    "url": "cg47.jpg",
    "origem": "nacional",
    "mao": "cg47.jpg"
}