{
    "id": "67",
    "palavra": "ACALENTAR",
    "acepcao": "Com a criança nos braços, fazer movimentos suaves para um lado e para outro do corpo, geralmente cantando, para que ela durma.",
    "exemplo": "O bebê estava chorando e eu o acalantei.",
    "video": "acalentarSm_Prog001.mp4",
    "libras": "BEBÊ CHORARcontinuativo EU ACALENTAR.",
    "img": "acalentarSm_Prog001.jpg",
    "assunto": "1",
    "assunto_title": "NENHUM",
    "classe": "VERBO",
    "url": "cg62.jpg",
    "origem": "nacional",
    "mao": "cg62.jpg"
}